asciimap/__init__.py
asciimap/__main__.py
asciimap/asciimap.py
asciimap/border.py
asciimap/maps.py
asciimap/data/ne_110m_admin_0_countries.README.html
asciimap/data/ne_110m_admin_0_countries.VERSION.txt
asciimap/data/ne_110m_admin_0_countries.cpg
asciimap/data/ne_110m_admin_0_countries.dbf
asciimap/data/ne_110m_admin_0_countries.prj
asciimap/data/ne_110m_admin_0_countries.shp
asciimap/data/ne_110m_admin_0_countries.shx
asciimap-1.0.0.dist-info/LICENSE
asciimap-1.0.0.dist-info/METADATA
asciimap-1.0.0.dist-info/WHEEL
asciimap-1.0.0.dist-info/entry_points.txt
asciimap-1.0.0.dist-info/top_level.txt
asciimap-1.0.0.dist-info/RECORD
