Metadata-Version: 2.1
Name: asciimap
Version: 1.0.0
Summary: Print countries in ASCII Art based on Natural Earth shape files.
Home-page: https://github.com/MaelStor/asciimap
Author: Mael Stor
Author-email: maelstor@posteo.de
License: GPL-3.0-or-later
Keywords: earth country print ascii art python spatial geo natural
Platform: UNKNOWN
Classifier: Development Status :: 5 - Production/Stable
Classifier: Environment :: Console
Classifier: Intended Audience :: System Administrators
Classifier: Intended Audience :: End Users/Desktop
Classifier: License :: OSI Approved :: GNU General Public License v3 or later (GPLv3+)
Classifier: Natural Language :: English
Classifier: Operating System :: POSIX :: Linux
Classifier: Programming Language :: Python :: 3 :: Only
Classifier: Topic :: Education
Classifier: Topic :: Multimedia
Classifier: Topic :: Multimedia :: Graphics
Classifier: Topic :: Multimedia :: Graphics :: Viewers
Classifier: Topic :: Multimedia :: Graphics :: Presentation
Classifier: Topic :: Scientific/Engineering :: GIS
Classifier: Topic :: Scientific/Engineering :: Visualization
Classifier: Topic :: Utilities
Requires-Python: >=3.6
Requires-Dist: numpy (<2.0.0,>=1.15.1)
